README.rst
setup.cfg
setup.py
HookWorker/__init__.py
HookWorker/api.py
HookWorker/cmd.py
HookWorker/worker.py
HookWorker.egg-info/PKG-INFO
HookWorker.egg-info/SOURCES.txt
HookWorker.egg-info/dependency_links.txt
HookWorker.egg-info/entry_points.txt
HookWorker.egg-info/requires.txt
HookWorker.egg-info/top_level.txt