Metadata-Version: 1.0
Name: HookWorker
Version: 0.0.6
Summary: Lightweight API to handle call and distribute them over a redis server
Home-page: https://github.com/Capitains/Hook-Worker
Author: Thibault Clerice
Author-email: leponteineptique@gmail.com
License: GNU GPL
Platform: UNKNOWN
